{
  "appointedReportingCompany": true,
  "agentDetails": {
    "agentActingOnBehalfOfCompany": true,
    "agentName": "some agent"
  },
  "reportingCompany": {
    "companyName": "Company Name ltd",
    "ctutr": "1123456789",
    "sameAsUltimateParent": false
  },
  "parentCompany": {
    "ultimateParent": {
      "companyName": "Company Name ltd",
      "isUk": true,
      "ctutr": "1123456789"
    }
  },
  "publicInfrastructure": true,
  "groupCompanyDetails": {
    "totalCompanies": 1,
    "accountingPeriod": {
      "startDate": "2019-02-18",
      "endDate": "2020-08-17"
    }
  },
  "submissionType": "revised",
  "revisedReturnDetails": "some details",
  "groupLevelElections": {
    "groupRatio": {
      "isElected": true,
      "groupEBITDAChargeableGains": true,
      "groupRatioBlended": {
        "isElected": true,
        "investorGroups": [{
          "groupName": "some investor group",
          "elections": ["groupRatioBlended", "groupEBITDA", "interestAllowanceAlternativeCalculation", "interestAllowanceNonConsolidatedInvestment", "interestAllowanceConsolidatedPartnership"]
        }, {
          "groupName": "some investor group",
          "elections": ["interestAllowanceAlternativeCalculation", "interestAllowanceNonConsolidatedInvestment", "interestAllowanceConsolidatedPartnership"]
        }]
      }
    },
    "interestAllowanceAlternativeCalculation": true,
    "interestAllowanceNonConsolidatedInvestment": {
      "isElected": true,
      "nonConsolidatedInvestments": [{
        "investmentName": "some Investment"
      }]
    },
    "interestAllowanceConsolidatedPartnership": {
      "isElected": true,
      "consolidatedPartnerships": [{
        "partnershipName": "some partner",
        "sautr": "1234567890"
      }]
    }
  },
  "ukCompanies": [{
    "companyName": "Company Name ltd",
    "utr": "1123456789",
    "consenting": true,
    "qicElection": true,
    "netTaxInterestExpense": 0,
    "netTaxInterestIncome": 50,
    "taxEBITDA": 5,
    "allocatedReactivations": {
      "currentPeriodReactivation": 2
    }
  }, {
    "companyName": "Company Name ltd",
    "utr": "1123456789",
    "consenting": true,
    "qicElection": true,
    "netTaxInterestExpense": 0,
    "netTaxInterestIncome": 50,
    "taxEBITDA": 5,
    "allocatedReactivations": {
      "currentPeriodReactivation": 2
    }
  }],
  "numberOfUkCompanies": 2,
  "aggregateNetTaxInterestExpense": 20,
  "aggregateTaxEBITDA": 5,
  "aggregateAllocatedRestrictions": 6,
  "aggregateAllocatedReactivations": 2,
  "angie": 1.11,
  "returnContainsEstimates": true,
  "groupSubjectToInterestRestrictions": false,
  "groupSubjectToInterestReactivation": true,
  "totalReactivation": 4,
  "totalRestrictions": 0,
  "groupLevelAmount": {
    "interestReactivationCap": 300,
    "interestAllowanceBroughtForward": 3,
    "interestAllowanceForPeriod": 4,
    "interestCapacityForPeriod": 5
  },
  "adjustedGroupInterest": {
    "qngie": 100,
    "groupEBITDA": 200,
    "groupRatio": 50
  }
}